schema_compare/__init__.py
schema_compare/main.py
schema_compare/report.py
schema_compare/drivers/__init__.py
schema_compare/drivers/postgresql/__init__.py
schema_compare/drivers/postgresql/connection.py
schema_compare-1.0.11.dist-info/LICENSE
schema_compare-1.0.11.dist-info/METADATA
schema_compare-1.0.11.dist-info/WHEEL
schema_compare-1.0.11.dist-info/entry_points.txt
schema_compare-1.0.11.dist-info/top_level.txt
schema_compare-1.0.11.dist-info/RECORD
