Metadata-Version: 2.1
Name: schema-compare
Version: 1.0.11
Summary: Compare database schemas
Author-email: Miguel Cardoso <msd.cardoso@hotmail.com>
License: Copyright 2022 Miguel Cardoso
Project-URL: Homepage, https://github.com/Tekaichi/schema-compare
Keywords: database,schema
Classifier: License :: OSI Approved :: MIT License
Classifier: Programming Language :: Python
Classifier: Programming Language :: Python :: 3
Requires-Python: >=3.9
License-File: LICENSE
Requires-Dist: psycopg2 ==2.9.9
Requires-Dist: SQLAlchemy ==2.0.31
Requires-Dist: pandas ==2.2.2
Requires-Dist: tomli ==2.0.1
